learns2/__init__.py
learns2/constants.py
learns2/featurizer.py
learns2/parser.py
learns2-0.0.20.dist-info/METADATA
learns2-0.0.20.dist-info/WHEEL
learns2-0.0.20.dist-info/top_level.txt
learns2-0.0.20.dist-info/RECORD
