Metadata-Version: 2.1
Name: learns2
Version: 0.0.20
Summary: For use with https://learns2.joepringle.dev
Home-page: https://github.com/joechip504/learns2/
Author: Joe Pringle
Author-email: joe@joepringle.dev
License: UNKNOWN
Platform: UNKNOWN
Classifier: Programming Language :: Python :: 3
Classifier: License :: OSI Approved :: MIT License
Classifier: Operating System :: OS Independent
Requires-Python: >=3.6
Requires-Dist: mpyq
Requires-Dist: s2protocol
Requires-Dist: numpy
